etcd_dynamic_config/__init__.py
etcd_dynamic_config/core/__init__.py
etcd_dynamic_config/core/base.py
etcd_dynamic_config/core/client.py
etcd_dynamic_config/core/config.py
etcd_dynamic_config/core/control_unit.py
etcd_dynamic_config/core/logging.py
etcd_dynamic_config/tests/__init__.py
etcd_dynamic_config/tests/test_basic.py
etcd_dynamic_config-0.2.4.dist-info/METADATA
etcd_dynamic_config-0.2.4.dist-info/WHEEL
etcd_dynamic_config-0.2.4.dist-info/top_level.txt
etcd_dynamic_config-0.2.4.dist-info/RECORD
