Metadata-Version: 2.4
Name: etcd-dynamic-config
Version: 0.2.4
Summary: A Python library for managing etcd-based configurations with caching and real-time updates
Author-email: Anton Irshenko <a_irshenko@example.com>
Maintainer-email: Anton Irshenko <a_irshenko@example.com>
License: MIT
Project-URL: Homepage, https://github.com/ton5169/etcd-dynamic-config
Project-URL: Documentation, https://github.com/ton5169/etcd-dynamic-config#readme
Project-URL: Repository, https://github.com/ton5169/etcd-dynamic-config
Project-URL: Issues, https://github.com/ton5169/etcd-dynamic-config/issues
Project-URL: Changelog, https://github.com/ton5169/etcd-dynamic-config/blob/main/CHANGELOG.md
Keywords: etcd,configuration,cache,watcher,async
Classifier: Development Status :: 3 - Alpha
Classifier: Intended Audience :: Developers
Classifier: License :: OSI Approved :: MIT License
Classifier: Operating System :: OS Independent
Classifier: Programming Language :: Python :: 3
Classifier: Programming Language :: Python :: 3.8
Classifier: Programming Language :: Python :: 3.9
Classifier: Programming Language :: Python :: 3.10
Classifier: Programming Language :: Python :: 3.11
Classifier: Programming Language :: Python :: 3.12
Classifier: Topic :: Software Development :: Libraries :: Python Modules
Classifier: Topic :: System :: Distributed Computing
Requires-Python: >=3.8
Requires-Dist: etcd3-py==0.1.6
Requires-Dist: ecs-logging==2.0.0
Provides-Extra: dev
Requires-Dist: pytest>=7.0.0; extra == "dev"
Requires-Dist: pytest-asyncio>=0.21.0; extra == "dev"
Requires-Dist: pytest-cov>=4.0.0; extra == "dev"
Requires-Dist: coverage>=7.0.0; extra == "dev"
Requires-Dist: black>=22.0.0; extra == "dev"
Requires-Dist: isort>=5.10.0; extra == "dev"
Requires-Dist: flake8>=4.0.0; extra == "dev"
Requires-Dist: mypy>=0.950; extra == "dev"
Requires-Dist: sphinx>=4.0.0; extra == "dev"
Requires-Dist: sphinx-rtd-theme>=1.0.0; extra == "dev"
Provides-Extra: docs
Requires-Dist: sphinx>=4.0.0; extra == "docs"
Requires-Dist: sphinx-rtd-theme>=1.0.0; extra == "docs"
